plib/classes/StateMachine.py
plib/classes/__init__.py
plib/classes/_defs.py
plib/test/classes/__init__.py
plib/test/classes/__main__.py
plib/test/classes/test_StateMachine.py
plib3.classes-0.11.dist-info/LICENSE.txt
plib3.classes-0.11.dist-info/METADATA
plib3.classes-0.11.dist-info/WHEEL
plib3.classes-0.11.dist-info/top_level.txt
plib3.classes-0.11.dist-info/RECORD
